R4ndomPojieJiaochengFanyi120aByQqsniper/README.md
R4ndomPojieJiaochengFanyi120aByQqsniper/__init__.py
R4ndomPojieJiaochengFanyi120aByQqsniper/__main__.py
R4ndomPojieJiaochengFanyi120aByQqsniper/file.pdf
R4ndomPojieJiaochengFanyi120aByQqsniper/index.html
r4ndom_pojie_jiaocheng_fanyi_1_20a_by_qqsniper-2024.3.2.0.dist-info/METADATA
r4ndom_pojie_jiaocheng_fanyi_1_20a_by_qqsniper-2024.3.2.0.dist-info/WHEEL
r4ndom_pojie_jiaocheng_fanyi_1_20a_by_qqsniper-2024.3.2.0.dist-info/entry_points.txt
r4ndom_pojie_jiaocheng_fanyi_1_20a_by_qqsniper-2024.3.2.0.dist-info/top_level.txt
r4ndom_pojie_jiaocheng_fanyi_1_20a_by_qqsniper-2024.3.2.0.dist-info/RECORD
